dummy.txt
casadi/__init__.py
casadi/_casadi.so
casadi/casadi-cli
casadi/casadi.py
casadi/cbc
casadi/clp
casadi/highs
casadi/libCbc.la
casadi/libCbc.so
casadi/libCbc.so.3
casadi/libCbc.so.3.10.11
casadi/libCbcSolver.la
casadi/libCbcSolver.so
casadi/libCbcSolver.so.3
casadi/libCbcSolver.so.3.10.11
casadi/libCgl.la
casadi/libCgl.so
casadi/libCgl.so.1
casadi/libCgl.so.1.10.8
casadi/libClp.la
casadi/libClp.so
casadi/libClp.so.1
casadi/libClp.so.1.14.9
casadi/libClpSolver.la
casadi/libClpSolver.so
casadi/libClpSolver.so.1
casadi/libClpSolver.so.1.14.9
casadi/libCoinUtils.la
casadi/libCoinUtils.so
casadi/libCoinUtils.so.3
casadi/libCoinUtils.so.3.11.10
casadi/libOsi.la
casadi/libOsi.so
casadi/libOsi.so.1
casadi/libOsi.so.1.13.9
casadi/libOsiCbc.la
casadi/libOsiCbc.so
casadi/libOsiCbc.so.3
casadi/libOsiCbc.so.3.10.11
casadi/libOsiClp.la
casadi/libOsiClp.so
casadi/libOsiClp.so.1
casadi/libOsiClp.so.1.14.9
casadi/libOsiCommonTests.la
casadi/libOsiCommonTests.so
casadi/libOsiCommonTests.so.1
casadi/libOsiCommonTests.so.1.13.9
casadi/libalpaqa-dl-loader.so
casadi/libalpaqa-dl-loader.so.1.0.0
casadi/libalpaqa.so
casadi/libalpaqa.so.1.0.0
casadi/libbonmin.la
casadi/libbonmin.so
casadi/libbonmin.so.4
casadi/libbonmin.so.4.8.9
casadi/libcasadi-tp-openblas.so
casadi/libcasadi-tp-openblas.so.0
casadi/libcasadi-tp-openblas.so.0.3
casadi/libcasadi.so
casadi/libcasadi.so.3.7
casadi/libcasadi_archiver_libzip.so
casadi/libcasadi_archiver_libzip.so.3.7
casadi/libcasadi_conic_cbc.so
casadi/libcasadi_conic_cbc.so.3.7
casadi/libcasadi_conic_clp.so
casadi/libcasadi_conic_clp.so.3.7
casadi/libcasadi_conic_daqp.so
casadi/libcasadi_conic_daqp.so.3.7
casadi/libcasadi_conic_gurobi.so
casadi/libcasadi_conic_gurobi.so.3.7
casadi/libcasadi_conic_highs.so
casadi/libcasadi_conic_highs.so.3.7
casadi/libcasadi_conic_ipqp.so
casadi/libcasadi_conic_ipqp.so.3.7
casadi/libcasadi_conic_nlpsol.so
casadi/libcasadi_conic_nlpsol.so.3.7
casadi-3.7.2.dist-info/METADATA
casadi-3.7.2.dist-info/RECORD
casadi-3.7.2.dist-info/WHEEL
